pamona/Pamona.py
pamona/__init__.py
pamona/eval.py
pamona/utils.py
pamona/visualization.py
pamona-0.1.0.dist-info/LICENSE.txt
pamona-0.1.0.dist-info/METADATA
pamona-0.1.0.dist-info/WHEEL
pamona-0.1.0.dist-info/top_level.txt
pamona-0.1.0.dist-info/RECORD
